keymaker/__init__.py
keymaker/printing.py
keymaker/s3.py
keymaker/util.py
keymaker/version.py
keymaker/iam/__init__.py
keymaker/iam/policies.py
keymaker-1.1.0.data/scripts/keymaker
keymaker-1.1.0.data/scripts/keymaker-create-account-for-iam-user
keymaker-1.1.0.dist-info/LICENSE
keymaker-1.1.0.dist-info/METADATA
keymaker-1.1.0.dist-info/WHEEL
keymaker-1.1.0.dist-info/top_level.txt
keymaker-1.1.0.dist-info/RECORD
